[
    {"german": "groß", "english": "big / tall / large", "example": "Das Haus ist groß."},
    {"german": "klein", "english": "small / short / tiny / little", "example": "Das Zimmer ist klein."},
    {"german": "lang", "english": "long / extended", "example": "Die Straße ist lang."},
    {"german": "kurz", "english": "short", "example": "Der Film ist kurz."},
    {"german": "breit / weit", "english": "wide / broad", "example": "Der Fluss ist breit."},
    {"german": "schmal / eng", "english": "narrow / tight / slim", "example": "Die Gasse ist schmal."},
    {"german": "hoch", "english": "high / tall / elevated", "example": "Der Turm ist hoch."},
    {"german": "niedrig / tief", "english": "low / deep", "example": "Das Wasser ist tief."},
    {"german": "leicht", "english": "light (weight)", "example": "Der Koffer ist leicht."},
    {"german": "schwer", "english": "heavy", "example": "Die Kiste ist schwer."},
    {"german": "dick", "english": "thick / fat / bulky", "example": "Das Buch ist dick."},
    {"german": "dünn / schlank", "english": "thin / slim / skinny", "example": "Das Papier ist dünn."},
    {"german": "stark / kräftig", "english": "strong / powerful", "example": "Der Wind ist stark."},
    {"german": "schwach", "english": "weak", "example": "Das Signal ist schwach."},
    {"german": "viel", "english": "much / many / a lot of", "example": "Ich habe viel Arbeit."},
    {"german": "wenig", "english": "little / few", "example": "Ich habe wenig Zeit."},
    {"german": "mehr", "english": "more / additional", "example": "Ich brauche mehr Platz."},
    {"german": "weniger", "english": "less / fewer", "example": "Ich möchte weniger Zucker."}
]
